cz_extended_conventional.py
cz_extended_conventional-0.1.0rc4.dist-info/METADATA
cz_extended_conventional-0.1.0rc4.dist-info/WHEEL
cz_extended_conventional-0.1.0rc4.dist-info/entry_points.txt
cz_extended_conventional-0.1.0rc4.dist-info/RECORD
