Metadata-Version: 2.3
Name: cz-extended-conventional
Version: 0.1.0rc4
Summary: An extended format of Commitizen's builtin cz_conventional_commit format.
License: MIT
Requires-Python: >=3.12,<4
Classifier: License :: OSI Approved :: MIT License
Classifier: Programming Language :: Python :: 3
Classifier: Programming Language :: Python :: 3.12
Classifier: Programming Language :: Python :: 3.13
Requires-Dist: commitizen (>=4.8.2,<5.0.0)
